metric_learn/__init__.py
metric_learn/_util.py
metric_learn/_version.py
metric_learn/base_metric.py
metric_learn/constraints.py
metric_learn/covariance.py
metric_learn/exceptions.py
metric_learn/itml.py
metric_learn/lfda.py
metric_learn/lmnn.py
metric_learn/lsml.py
metric_learn/mlkr.py
metric_learn/mmc.py
metric_learn/nca.py
metric_learn/rca.py
metric_learn/scml.py
metric_learn/sdml.py
metric_learn/sklearn_shims.py
metric_learn-0.7.0.dist-info/LICENSE.txt
metric_learn-0.7.0.dist-info/METADATA
metric_learn-0.7.0.dist-info/WHEEL
metric_learn-0.7.0.dist-info/top_level.txt
metric_learn-0.7.0.dist-info/RECORD
