Metadata-Version: 2.1
Name: metric-learn
Version: 0.7.0
Summary: Python implementations of metric learning algorithms
Home-page: http://github.com/scikit-learn-contrib/metric-learn
Author: ['CJ Carey', 'Yuan Tang', 'William de Vazelhes', 'Aurélien Bellet', 'Nathalie Vauquier']
Author-email: ccarey@cs.umass.edu
License: MIT
Keywords: Metric Learning,Large Margin Nearest Neighbor,Information Theoretic Metric Learning,Sparse Determinant Metric Learning,Least Squares Metric Learning,Neighborhood Components Analysis,Local Fisher Discriminant Analysis,Relative Components Analysis,Mahalanobis Metric for Clustering,Metric Learning for Kernel Regression
Classifier: Development Status :: 4 - Beta
Classifier: License :: OSI Approved :: MIT License
Classifier: Programming Language :: Python :: 3
Classifier: Operating System :: OS Independent
Classifier: Intended Audience :: Science/Research
Classifier: Topic :: Scientific/Engineering
Requires-Python: >=3.6
License-File: LICENSE.txt
Requires-Dist: numpy >=1.11.0
Requires-Dist: scipy >=0.17.0
Requires-Dist: scikit-learn >=0.21.3
Provides-Extra: demo
Requires-Dist: matplotlib ; extra == 'demo'
Provides-Extra: docs
Requires-Dist: sphinx ; extra == 'docs'
Requires-Dist: sphinx-rtd-theme ; extra == 'docs'
Requires-Dist: numpydoc ; extra == 'docs'
Requires-Dist: sphinx-gallery ; extra == 'docs'
Requires-Dist: matplotlib ; extra == 'docs'
Provides-Extra: sdml
Requires-Dist: skggm >=0.2.9 ; extra == 'sdml'
